adder.v
`timescale 1ns/1ns
module HalfAdder (
    sum,carry,A,B
);
    input A,B;
    output sum,carry;
    not #1 (Abar,A);
    not #1 (Bbar,B);
    and #1 (ABbar,A,Bbar);
    and #1 (AbarB,Abar,B);
    or #1 (sum,ABbar,AbarB);
    and #1 (carry,A,B);
endmodule
module FullAdder (
    A,B,carryin,carryout,sum
);
    input A,B,carryin;
    output carryout,sum;
    wire carrymid1,carrymid2,summid;
    HalfAdder HA1(.sum(summid),.carry(carrymid1),.A(A),.B(B));
    HalfAdder HA2(.sum(sum),.carry(carrymid2),.A(summid),.B(carryin));
    or #1 (carryout,carrymid1,carrymid2);
endmodule
module RCA (
    input wire[3:0] in1, input wire[3:0] in2, output wire[3:0] out, input wire cin, output wire carry
);
    wire c1,c2,c3;
    FullAdder F1(.A(in1[0]),.B(in2[0]),.sum(out[0]),.carryin(cin),.carryout(c1));
    FullAdder F2(.A(in1[1]),.B(in2[1]),.sum(out[1]),.carryin(c1),.carryout(c2));
    FullAdder F3(.A(in1[2]),.B(in2[2]),.sum(out[2]),.carryin(c2),.carryout(c3));
    FullAdder F4(.A(in1[3]),.B(in2[3]),.sum(out[3]),.carryin(c3),.carryout(carry));
endmodule
// For the first case the delay in obtaining sum is 9ns
// For the first case the delay in obtaining carry is 7ns
// After changing the input the sum stabilizes after 5ns. The imput changes at 20ns and the sum finally stabilizes at 25ns

HA_tb.v
`timescale 1ns/1ns

module HA_tb;
reg a,b;
wire sum,carry;
HalfAdder HA(.sum(sum),.carry(carry),.A(a),.B(b));
initial begin
    $dumpfile("HA_tb.vcd");
    $dumpvars(0,HA_tb);
    a=1;b=1; #10;
    a=0;b=1; #10;
    a=1;b=0; #10;
    a=0;b=1; #10;
    #10 $finish;
end
endmodule

HA_tb.vcd
$date
	Tue Sep 12 15:15:08 2023
$end
$version
	Icarus Verilog
$end
$timescale
	1ns
$end
$scope module HA_tb $end
$var wire 1 ! sum $end
$var wire 1 " carry $end
$var reg 1 # a $end
$var reg 1 $ b $end
$scope module HA $end
$var wire 1 # A $end
$var wire 1 % ABbar $end
$var wire 1 & Abar $end
$var wire 1 ' AbarB $end
$var wire 1 $ B $end
$var wire 1 ( Bbar $end
$var wire 1 " carry $end
$var wire 1 ! sum $end
$upscope $end
$upscope $end
$enddefinitions $end
$comment Show the parameter values. $end
$dumpall
$end
#0
$dumpvars
x(
x'
x&
x%
1$
1#
x"
x!
$end
#1
0(
0&
1"
#2
0%
0'
#3
0!
#10
0#
#11
1&
0"
#12
1'
#13
1!
#20
0$
1#
#21
1(
0'
0&
#22
1%
0!
#23
1!
#30
1$
0#
#31
0(
1&
0%
#32
1'
0!
#33
1!
