adder.v
`timescale 1ns/1ns
module HalfAdder (
    sum,carry,A,B
);
    input A,B;
    output sum,carry;
    not #1 (Abar,A);
    not #1 (Bbar,B);
    and #1 (ABbar,A,Bbar);
    and #1 (AbarB,Abar,B);
    or #1 (sum,ABbar,AbarB);
    and #1 (carry,A,B);
endmodule
module FullAdder (
    A,B,carryin,carryout,sum
);
    input A,B,carryin;
    output carryout,sum;
    wire carrymid1,carrymid2,summid;
    HalfAdder HA1(.sum(summid),.carry(carrymid1),.A(A),.B(B));
    HalfAdder HA2(.sum(sum),.carry(carrymid2),.A(summid),.B(carryin));
    or #1 (carryout,carrymid1,carrymid2);
endmodule
module RCA (
    input wire[3:0] in1, input wire[3:0] in2, output wire[3:0] out, input wire cin, output wire carry
);
    wire c1,c2,c3;
    FullAdder F1(.A(in1[0]),.B(in2[0]),.sum(out[0]),.carryin(cin),.carryout(c1));
    FullAdder F2(.A(in1[1]),.B(in2[1]),.sum(out[1]),.carryin(c1),.carryout(c2));
    FullAdder F3(.A(in1[2]),.B(in2[2]),.sum(out[2]),.carryin(c2),.carryout(c3));
    FullAdder F4(.A(in1[3]),.B(in2[3]),.sum(out[3]),.carryin(c3),.carryout(carry));
endmodule
// For the first case the delay in obtaining sum is 9ns
// For the first case the delay in obtaining carry is 7ns
// After changing the input the sum stabilizes after 5ns. The imput changes at 20ns and the sum finally stabilizes at 25ns

RCA_tb.v
`timescale 1ns/1ps

module RCA_tb;
reg [3:0] in1; reg[3:0] in2; reg cin;
wire [3:0] out; wire carry;
RCA RCA4(.out(out),.in1(in1),.in2(in2),.cin(cin),.carry(carry));
initial begin
    $dumpfile("RCA_tb.vcd");
    $dumpvars(0,RCA_tb);
    in1=4'b1111;in2=4'b0000;cin=1; #20;
    in1=4'b0000;in2=4'b0001;cin=0;#20
    #10 $finish;
end
endmodule

RCA_tb.vcd
$date
	Tue Sep 12 18:46:40 2023
$end
$version
	Icarus Verilog
$end
$timescale
	1ps
$end
$scope module RCA_tb $end
$var wire 4 ! out [3:0] $end
$var wire 1 " carry $end
$var reg 1 # cin $end
$var reg 4 $ in1 [3:0] $end
$var reg 4 % in2 [3:0] $end
$scope module RCA4 $end
$var wire 1 # cin $end
$var wire 4 & in1 [3:0] $end
$var wire 4 ' in2 [3:0] $end
$var wire 4 ( out [3:0] $end
$var wire 1 " carry $end
$var wire 1 ) c3 $end
$var wire 1 * c2 $end
$var wire 1 + c1 $end
$scope module F1 $end
$var wire 1 , A $end
$var wire 1 - B $end
$var wire 1 # carryin $end
$var wire 1 + carryout $end
$var wire 1 . summid $end
$var wire 1 / sum $end
$var wire 1 0 carrymid2 $end
$var wire 1 1 carrymid1 $end
$scope module HA1 $end
$var wire 1 , A $end
$var wire 1 2 ABbar $end
$var wire 1 3 Abar $end
$var wire 1 4 AbarB $end
$var wire 1 - B $end
$var wire 1 5 Bbar $end
$var wire 1 1 carry $end
$var wire 1 . sum $end
$upscope $end
$scope module HA2 $end
$var wire 1 . A $end
$var wire 1 6 ABbar $end
$var wire 1 7 Abar $end
$var wire 1 8 AbarB $end
$var wire 1 # B $end
$var wire 1 9 Bbar $end
$var wire 1 0 carry $end
$var wire 1 / sum $end
$upscope $end
$upscope $end
$scope module F2 $end
$var wire 1 : A $end
$var wire 1 ; B $end
$var wire 1 + carryin $end
$var wire 1 * carryout $end
$var wire 1 < summid $end
$var wire 1 = sum $end
$var wire 1 > carrymid2 $end
$var wire 1 ? carrymid1 $end
$scope module HA1 $end
$var wire 1 : A $end
$var wire 1 @ ABbar $end
$var wire 1 A Abar $end
$var wire 1 B AbarB $end
$var wire 1 ; B $end
$var wire 1 C Bbar $end
$var wire 1 ? carry $end
$var wire 1 < sum $end
$upscope $end
$scope module HA2 $end
$var wire 1 < A $end
$var wire 1 D ABbar $end
$var wire 1 E Abar $end
$var wire 1 F AbarB $end
$var wire 1 + B $end
$var wire 1 G Bbar $end
$var wire 1 > carry $end
$var wire 1 = sum $end
$upscope $end
$upscope $end
$scope module F3 $end
$var wire 1 H A $end
$var wire 1 I B $end
$var wire 1 * carryin $end
$var wire 1 ) carryout $end
$var wire 1 J summid $end
$var wire 1 K sum $end
$var wire 1 L carrymid2 $end
$var wire 1 M carrymid1 $end
$scope module HA1 $end
$var wire 1 H A $end
$var wire 1 N ABbar $end
$var wire 1 O Abar $end
$var wire 1 P AbarB $end
$var wire 1 I B $end
$var wire 1 Q Bbar $end
$var wire 1 M carry $end
$var wire 1 J sum $end
$upscope $end
$scope module HA2 $end
$var wire 1 J A $end
$var wire 1 R ABbar $end
$var wire 1 S Abar $end
$var wire 1 T AbarB $end
$var wire 1 * B $end
$var wire 1 U Bbar $end
$var wire 1 L carry $end
$var wire 1 K sum $end
$upscope $end
$upscope $end
$scope module F4 $end
$var wire 1 V A $end
$var wire 1 W B $end
$var wire 1 ) carryin $end
$var wire 1 " carryout $end
$var wire 1 X summid $end
$var wire 1 Y sum $end
$var wire 1 Z carrymid2 $end
$var wire 1 [ carrymid1 $end
$scope module HA1 $end
$var wire 1 V A $end
$var wire 1 \ ABbar $end
$var wire 1 ] Abar $end
$var wire 1 ^ AbarB $end
$var wire 1 W B $end
$var wire 1 _ Bbar $end
$var wire 1 [ carry $end
$var wire 1 X sum $end
$upscope $end
$scope module HA2 $end
$var wire 1 X A $end
$var wire 1 ` ABbar $end
$var wire 1 a Abar $end
$var wire 1 b AbarB $end
$var wire 1 ) B $end
$var wire 1 c Bbar $end
$var wire 1 Z carry $end
$var wire 1 Y sum $end
$upscope $end
$upscope $end
$upscope $end
$upscope $end
$enddefinitions $end
$comment Show the parameter values. $end
$dumpall
$end
#0
$dumpvars
xc
xb
xa
x`
x_
x^
x]
x\
x[
xZ
xY
xX
0W
1V
xU
xT
xS
xR
xQ
xP
xO
xN
xM
xL
xK
xJ
0I
1H
xG
xF
xE
xD
xC
xB
xA
x@
x?
x>
x=
x<
0;
1:
x9
x8
x7
x6
x5
x4
x3
x2
x1
x0
x/
x.
0-
1,
x+
x*
x)
bx (
b0 '
b1111 &
b0 %
b1111 $
1#
x"
bx !
$end
#1000
15
04
1C
0B
1Q
0P
1_
0^
03
01
0A
0?
0O
0M
0]
0[
09
#2000
12
1@
1N
1\
06
#3000
1.
1<
1J
1X
#4000
07
10
0E
0S
0a
#5000
08
1+
0F
0T
0b
#6000
bx0 !
bx0 (
0/
0G
1>
#7000
0D
1*
#8000
bx00 !
bx00 (
0=
0U
1L
#9000
0R
1)
#10000
bx000 !
bx000 (
0K
0c
1Z
#11000
0`
1"
#12000
b0 !
b0 (
0Y
#20000
1-
0,
0:
0H
0V
0#
b1 %
b1 '
b0 $
b0 &
#21000
05
13
02
1A
0@
1O
0N
1]
0\
19
00
#22000
14
0.
0<
0J
0X
16
0+
#23000
1.
17
06
1E
1S
0L
1a
0Z
b1 !
b1 (
1/
1G
0>
#24000
07
16
b0 !
b0 (
0/
1T
0)
1b
0"
0*
#25000
1/
1K
1c
0b
b1101 !
b1101 (
1Y
1U
0T
#26000
0Y
b1 !
b1 (
0K
